setup.py
guiCreate/PastV1.py
guiCreate/__init__.py
guiCreate/base.py
guiCreate/main.py
guiCreate.egg-info/PKG-INFO
guiCreate.egg-info/SOURCES.txt
guiCreate.egg-info/dependency_links.txt
guiCreate.egg-info/requires.txt
guiCreate.egg-info/top_level.txt
guiCreate/noneVisible/__init__.py
guiCreate/noneVisible/obj.py
guiCreate/visible/__init__.py
guiCreate/visible/obj.py